cgatshowcase/__init__.py
cgatshowcase/entry.py
cgatshowcase/pipeline_transdiffexprs.py
cgatshowcase/version.py
cgatshowcase/R/DESeq2_lrt.R
cgatshowcase/R/DESeq2_wald.R
cgatshowcase-0.1.2.dist-info/METADATA
cgatshowcase-0.1.2.dist-info/RECORD
cgatshowcase-0.1.2.dist-info/WHEEL
cgatshowcase-0.1.2.dist-info/entry_points.txt
cgatshowcase-0.1.2.dist-info/top_level.txt
